at_common_schemas/base.py
at_common_schemas/core/candlestick.py
at_common_schemas/core/economics.py
at_common_schemas/core/entry.py
at_common_schemas/core/news.py
at_common_schemas/core/quote.py
at_common_schemas/core/technical.py
at_common_schemas/core/stock/analyst.py
at_common_schemas/core/stock/calendar.py
at_common_schemas/core/stock/company.py
at_common_schemas/core/stock/financial.py
at_common_schemas/core/stock/similarity.py
at_common_schemas-1.1.13.dist-info/METADATA
at_common_schemas-1.1.13.dist-info/WHEEL
at_common_schemas-1.1.13.dist-info/top_level.txt
at_common_schemas-1.1.13.dist-info/RECORD
