Metadata-Version: 2.4
Name: at-common-schemas
Version: 1.1.13
Summary: Common schemas used by Apex Trader
Author: Rui Chen
Project-URL: Homepage, https://github.com/apex-trader/at-common-schemas
Project-URL: Bug Tracker, https://github.com/apex-trader/at-common-schemas/issues
Requires-Python: >=3.11
Requires-Dist: pydantic>=2.10.6
Requires-Dist: annotated-types>=0.7.0
Requires-Dist: typing_extensions>=4.12.2
